{
  "title_lines": ["MADE WITH", "CLIPWRIGHT"],
  "tagline": "",
  "url": "",
  "status_pill": "",
  "bg_rgb": [255, 255, 255],
  "accent_rgb": [0, 0, 0],
  "secondary_rgb": [120, 120, 120],
  "text_rgb": [0, 0, 0],
  "dim_rgb": [120, 120, 120],
  "grid_rgb": [245, 245, 245],
  "font_title": "",
  "font_title_index": 0,
  "font_title_size": 96,
  "font_body": "",
  "font_body_index": 0,
  "font_body_size": 28,
  "font_small_size": 22,
  "width": 1080,
  "height": 1920,
  "fps": 60,
  "duration": 2.0,
  "show_grid": false,
  "show_brackets": false
}
